docasur/__init__.py
docasur/metadata.py
docasur-0.0.1.dist-info/METADATA
docasur-0.0.1.dist-info/WHEEL
docasur-0.0.1.dist-info/entry_points.txt
docasur-0.0.1.dist-info/RECORD
